general_robotics_toolbox/__init__.py
general_robotics_toolbox/general_robotics_toolbox.py
general_robotics_toolbox/general_robotics_toolbox_invkin.py
general_robotics_toolbox/robotraconteur.py
general_robotics_toolbox/ros_msg.py
general_robotics_toolbox/ros_tf.py
general_robotics_toolbox/tesseract.py
general_robotics_toolbox/urdf.py
general_robotics_toolbox-0.7.3.dist-info/licenses/LICENSE
general_robotics_toolbox-0.7.3.dist-info/METADATA
general_robotics_toolbox-0.7.3.dist-info/WHEEL
general_robotics_toolbox-0.7.3.dist-info/top_level.txt
general_robotics_toolbox-0.7.3.dist-info/RECORD
