Metadata-Version: 2.4
Name: general_robotics_toolbox
Version: 0.7.3
Summary: General robotics toolbox developed by RPI
Home-page: https://github.com/rpiRobotics/rpi_general_robotics_toolbox_py
Author: John Wason
Author-email: wason@wasontech.com
Classifier: Programming Language :: Python :: 3
Classifier: License :: OSI Approved :: BSD License
Classifier: Operating System :: OS Independent
Requires-Python: >=2.7
License-File: LICENSE
Requires-Dist: numpy
Requires-Dist: urdf_parser_py
Requires-Dist: pyyaml
Provides-Extra: test
Requires-Dist: pytest; extra == "test"
Provides-Extra: urdf
Requires-Dist: rospkg; extra == "urdf"
Requires-Dist: xacro; extra == "urdf"
Provides-Extra: tesseract
Requires-Dist: tesseract-robotics>=0.2.0; extra == "tesseract"
Dynamic: author
Dynamic: author-email
Dynamic: classifier
Dynamic: description
Dynamic: description-content-type
Dynamic: home-page
Dynamic: license-file
Dynamic: provides-extra
Dynamic: requires-dist
Dynamic: requires-python
Dynamic: summary
